terse/__init__.py
terse/in_directory.py
terse/invoke.py
terse/on_exit.py
terse/future/__init__.py
terse/future/on_exit.py
terse/test/__init__.py
terse/test/test_chdir.py
terse/test/test_invoke.py
terse/test/test_invoke_helper.py
terse/test/test_on_exit.py
terse-0.0.9.dist-info/DESCRIPTION.rst
terse-0.0.9.dist-info/METADATA
terse-0.0.9.dist-info/RECORD
terse-0.0.9.dist-info/WHEEL
terse-0.0.9.dist-info/metadata.json
terse-0.0.9.dist-info/top_level.txt
