Metadata-Version: 2.0
Name: terse
Version: 0.0.9
Summary: a collection of function decorators to handle common procedures done on the entry and exit points.
Home-page: https://github.com/cjlucas85/terse
Author: Chad Lucas
Author-email: cjlucas85@gmail.com
License: UNKNOWN
Platform: UNKNOWN
Classifier: Development Status :: 4 - Beta
Classifier: Programming Language :: Python :: 2.7
Classifier: Programming Language :: Python :: 3.5
Classifier: License :: OSI Approved :: BSD License
Classifier: Operating System :: OS Independent
